[
  {
    "anonymous": false,
    "inputs": [
      {
        "indexed": true,
        "internalType": "uint256",
        "name": "licenseId",
        "type": "uint256"
      },
      {
        "indexed": false,
        "internalType": "string",
        "name": "termsURI",
        "type": "string"
      },
      {
        "indexed": false,
        "internalType": "enum LicenseRepository.Rights",
        "name": "rights",
        "type": "uint8"
      }
    ],
    "name": "LicenseTemplateCreated",
    "type": "event"
  },
  {
    "inputs": [
      {
        "internalType": "enum LicenseRepository.Rights",
        "name": "rights",
        "type": "uint8"
      },
      {
        "internalType": "string",
        "name": "termsUri",
        "type": "string"
      }
    ],
    "name": "addTemplate",
    "outputs": [
      {
        "internalType": "uint256",
        "name": "",
        "type": "uint256"
      }
    ],
    "stateMutability": "nonpayable",
    "type": "function"
  },
  {
    "inputs": [
      {
        "internalType": "uint256",
        "name": "index",
        "type": "uint256"
      }
    ],
    "name": "licenseTemplateAt",
    "outputs": [
      {
        "components": [
          {
            "internalType": "enum LicenseRepository.Rights",
            "name": "rights",
            "type": "uint8"
          },
          {
            "internalType": "string",
            "name": "termsURI",
            "type": "string"
          }
        ],
        "internalType": "struct LicenseRepository.License",
        "name": "",
        "type": "tuple"
      }
    ],
    "stateMutability": "view",
    "type": "function"
  },
  {
    "inputs": [
      {
        "internalType": "uint256",
        "name": "",
        "type": "uint256"
      }
    ],
    "name": "licenseTemplates",
    "outputs": [
      {
        "internalType": "enum LicenseRepository.Rights",
        "name": "rights",
        "type": "uint8"
      },
      {
        "internalType": "string",
        "name": "termsURI",
        "type": "string"
      }
    ],
    "stateMutability": "view",
    "type": "function"
  },
  {
    "inputs": [],
    "name": "totalLicenseTemplates",
    "outputs": [
      {
        "internalType": "uint256",
        "name": "",
        "type": "uint256"
      }
    ],
    "stateMutability": "view",
    "type": "function"
  }
]
